<?xml version="1.0" encoding="utf-8" ?>
<c2layout>
    <name>Layout 1</name>
    <sid>4765895634742318</sid>
    <event-sheet>Event sheet 7</event-sheet>
    <size>
        <width>3000</width>
        <height>640</height>
    </size>
    <margins>
        <horizontal>0</horizontal>
        <vertical>0</vertical>
    </margins>
    <unbounded-scrolling>0</unbounded-scrolling>
    <layers>
        <layer name="Layer 0" sid="6344186816147636">
            <initially-visible>1</initially-visible>
            <background-color>255,255,255</background-color>
            <transparent>0</transparent>
            <parallax>
                <x>1</x>
                <y>1</y>
            </parallax>
            <zoom-rate>1</zoom-rate>
            <opacity>1</opacity>
            <force-own-texture>0</force-own-texture>
            <global>0</global>
            <use-render-cells>0</use-render-cells>
            <blend-mode>0</blend-mode>
            <effect-fallback>0</effect-fallback>
            <instances>
                <instance type="TiledBackground36" uid="580">
                    <properties>
                        <initial-visibility>Visible</initial-visibility>
                        <hotspot>Top-left</hotspot>
                    </properties>
                    <blend-mode>0</blend-mode>
                    <effect-fallback>0</effect-fallback>
                    <world>
                        <x>-1</x>
                        <y>-7</y>
                        <z>0</z>
                        <width>1134</width>
                        <height>646</height>
                        <depth>0</depth>
                        <hotspotX>0</hotspotX>
                        <hotspotY>0</hotspotY>
                        <angle>0</angle>
                        <opacity>1</opacity>
                    </world>
                </instance>
                <instance type="Sprite83" uid="581">
                    <properties>
                        <initial-visibility>Visible</initial-visibility>
                        <initial-animation>Default</initial-animation>
                        <initial-frame>0</initial-frame>
                        <collisions>Enabled</collisions>
                    </properties>
                    <blend-mode>0</blend-mode>
                    <effect-fallback>0</effect-fallback>
                    <world>
                        <x>553</x>
                        <y>310</y>
                        <z>0</z>
                        <width>698</width>
                        <height>541</height>
                        <depth>0</depth>
                        <hotspotX>0.50082916</hotspotX>
                        <hotspotY>0.501035213</hotspotY>
                        <angle>0</angle>
                        <opacity>1</opacity>
                    </world>
                </instance>
                <instance type="Sprite84" uid="582">
                    <properties>
                        <initial-visibility>Visible</initial-visibility>
                        <initial-animation>Default</initial-animation>
                        <initial-frame>0</initial-frame>
                        <collisions>Enabled</collisions>
                    </properties>
                    <blend-mode>0</blend-mode>
                    <effect-fallback>0</effect-fallback>
                    <world>
                        <x>549</x>
                        <y>87</y>
                        <z>0</z>
                        <width>186</width>
                        <height>38</height>
                        <depth>0</depth>
                        <hotspotX>0.5</hotspotX>
                        <hotspotY>0.5</hotspotY>
                        <angle>0</angle>
                        <opacity>1</opacity>
                    </world>
                </instance>
                <instance type="Text7" uid="583">
                    <properties>
                        <text>Kamu Harus Mendapatkan Kunci Berwarna Hijau Sebanyak 3 Buah Agar Bisa Membuka Sebuah Pintu Dan Melaju Ke Level Selanjutnya. Berhati-hatilah Terhadap Musuh Yang Senantiasa Mengintai Kamu</text>
                        <initial-visibility>Visible</initial-visibility>
                        <font>Algerian,-35,700,0</font>
                        <color>0,0,0</color>
                        <horizontal-alignment>Left</horizontal-alignment>
                        <vertical-alignment>Top</vertical-alignment>
                        <hotspot>Top-left</hotspot>
                        <wrapping>Word</wrapping>
                        <line-height>0</line-height>
                    </properties>
                    <blend-mode>0</blend-mode>
                    <effect-fallback>0</effect-fallback>
                    <world>
                        <x>245</x>
                        <y>173</y>
                        <z>0</z>
                        <width>596</width>
                        <height>383</height>
                        <depth>0</depth>
                        <hotspotX>0</hotspotX>
                        <hotspotY>0</hotspotY>
                        <angle>0</angle>
                        <opacity>1</opacity>
                    </world>
                </instance>
                <instance type="Sprite14" uid="584">
                    <properties>
                        <initial-visibility>Visible</initial-visibility>
                        <initial-animation>Default</initial-animation>
                        <initial-frame>0</initial-frame>
                        <collisions>Enabled</collisions>
                    </properties>
                    <blend-mode>0</blend-mode>
                    <effect-fallback>0</effect-fallback>
                    <world>
                        <x>554</x>
                        <y>549</y>
                        <z>0</z>
                        <width>93</width>
                        <height>96</height>
                        <depth>0</depth>
                        <hotspotX>0.505376339</hotspotX>
                        <hotspotY>0.5</hotspotY>
                        <angle>0</angle>
                        <opacity>1</opacity>
                    </world>
                </instance>
            </instances>
            <effects />
        </layer>
    </layers>
    <nonworld-instances />
    <effects />
</c2layout>
